.bumpversion.cfg
COPYING.BSD
COPYING.EPL
MANIFEST.in
antilles-tools.spec
dev-requirements.txt
requirements.txt
setup.cfg
setup.py
test-requirements.txt
tox.ini
antilles/__init__.py
antilles/tools/__init__.py
antilles/tools/main.py
antilles/tools/passwd.py
antilles_tools.egg-info/PKG-INFO
antilles_tools.egg-info/SOURCES.txt
antilles_tools.egg-info/dependency_links.txt
antilles_tools.egg-info/entry_points.txt
antilles_tools.egg-info/namespace_packages.txt
antilles_tools.egg-info/not-zip-safe
antilles_tools.egg-info/requires.txt
antilles_tools.egg-info/top_level.txt
src/obfuscator.pyx
tests/__init__.py