Metadata-Version: 1.2
Name: antilles-tools
Version: 1.0.0
Summary: Tools collection for antilles project
Home-page: UNKNOWN
License: BSD-3 and EPL-1.0
Keywords: hpc,antilles
Platform: UNKNOWN
Classifier: Development Status :: 2 - Pre-Alpha
Classifier: Programming Language :: Python :: 2
Classifier: Programming Language :: Python :: 2.6
Classifier: Programming Language :: Python :: 2.7
Classifier: Operating System :: POSIX
Classifier: Operating System :: POSIX :: Linux
Classifier: Topic :: Software Development :: Libraries
Classifier: Topic :: Software Development :: Libraries :: Python Modules
Requires-Python: ~=2.6
